{
  "sheetsById": {
    "Mainv3": {
      "staticOverrides": {
        "byObject": {}
      },
      "sequence": {
        "subUnitsPerUnit": 30,
        "length": 43.99,
        "type": "PositionalSequence",
        "tracksByObject": {
          "Camera": {
            "trackData": {
              "pR6XONmeJe": {
                "type": "BasicKeyframedTrack",
                "__debugName": "Camera:[\"position\",\"x\"]",
                "keyframes": [
                  {
                    "id": "OF7w4_nyrb",
                    "position": 0,
                    "connectedRight": true,
                    "handles": [
                      0.5,
                      1,
                      0.5,
                      0
                    ],
                    "type": "bezier",
                    "value": 0
                  },
                  {
                    "id": "mVMg_F_jVE",
                    "position": 4,
                    "connectedRight": true,
                    "handles": [
                      0.5,
                      1,
                      0.5,
                      0
                    ],
                    "type": "bezier",
                    "value": 0
                  },
                  {
                    "id": "JpV9nwSCpC",
                    "position": 6,
                    "connectedRight": true,
                    "handles": [
                      0.5,
                      1,
                      0.5,
                      0
                    ],
                    "type": "bezier",
                    "value": -13.80545197590395
                  },
                  {
                    "id": "UfSo771fm9",
                    "position": 8,
                    "connectedRight": true,
                    "handles": [
                      0.5,
                      1,
                      0.5,
                      0
                    ],
                    "type": "bezier",
                    "value": -14.88743670576461
                  },
                  {
                    "id": "Dy57Shmxcj",
                    "position": 12,
                    "connectedRight": true,
                    "handles": [
                      0.5,
                      1,
                      0.5,
                      0
                    ],
                    "type": "bezier",
                    "value": 0
                  },
                  {
                    "id": "fRpL-Exdx_",
                    "position": 14,
                    "connectedRight": true,
                    "handles": [
                      0.5,
                      1,
                      0.5,
                      0
                    ],
                    "type": "bezier",
                    "value": -6.338529970182039
                  },
                  {
                    "id": "xkQ0OI8snJ",
                    "position": 16,
                    "connectedRight": true,
                    "handles": [
                      0.5,
                      1,
                      0.5,
                      0
                    ],
                    "type": "bezier",
                    "value": -5.522134067567624
                  },
                  {
                    "id": "4jUAUgYBZv",
                    "position": 20,
                    "connectedRight": true,
                    "handles": [
                      0.5,
                      1,
                      0.5,
                      0
                    ],
                    "type": "bezier",
                    "value": 0
                  },
                  {
                    "id": "_apTeg_cx4",
                    "position": 22,
                    "connectedRight": true,
                    "handles": [
                      0.5,
                      1,
                      0.5,
                      0
                    ],
                    "type": "bezier",
                    "value": 7.615745702856604
                  },
                  {
                    "id": "LY5DUw_9Dp",
                    "position": 24,
                    "connectedRight": true,
                    "handles": [
                      0.5,
                      1,
                      0.5,
                      0
                    ],
                    "type": "bezier",
                    "value": 6.084608911296353
                  },
                  {
                    "id": "rpC1y5DrpY",
                    "position": 28,
                    "connectedRight": true,
                    "handles": [
                      0.5,
                      1,
                      0.5,
                      0
                    ],
                    "type": "bezier",
                    "value": 0
                  },
                  {
                    "id": "SbeNxbuJnn",
                    "position": 30,
                    "connectedRight": true,
                    "handles": [
                      0.5,
                      1,
                      0.5,
                      0
                    ],
                    "type": "bezier",
                    "value": 15.845899826475161
                  },
                  {
                    "id": "94dkGYUN_y",
                    "position": 32,
                    "connectedRight": true,
                    "handles": [
                      0.5,
                      1,
                      0.5,
                      0
                    ],
                    "type": "bezier",
                    "value": 14.810090747259268
                  },
                  {
                    "id": "YamUGPQQWF",
                    "position": 36,
                    "connectedRight": true,
                    "handles": [
                      0.5,
                      1,
                      0.5,
                      0
                    ],
                    "type": "bezier",
                    "value": 0
                  }
                ]
              },
              "dDvO1bpiqm": {
                "type": "BasicKeyframedTrack",
                "__debugName": "Camera:[\"position\",\"y\"]",
                "keyframes": [
                  {
                    "id": "X0SIKYi9b0",
                    "position": 0,
                    "connectedRight": true,
                    "handles": [
                      0.5,
                      1,
                      0.5,
                      0
                    ],
                    "type": "bezier",
                    "value": 0
                  },
                  {
                    "id": "PA_ZJ1aAP1",
                    "position": 4,
                    "connectedRight": true,
                    "handles": [
                      0.5,
                      1,
                      0.5,
                      0
                    ],
                    "type": "bezier",
                    "value": 20.479472219256753
                  },
                  {
                    "id": "kAzIhjI0l9",
                    "position": 6,
                    "connectedRight": true,
                    "handles": [
                      0.5,
                      1,
                      0.5,
                      0
                    ],
                    "type": "bezier",
                    "value": 0.7714907817921208
                  },
                  {
                    "id": "ZfvX1d9CpZ",
                    "position": 8,
                    "connectedRight": true,
                    "handles": [
                      0.5,
                      1,
                      0.5,
                      0
                    ],
                    "type": "bezier",
                    "value": 0.7713679953868464
                  },
                  {
                    "id": "HTAVRAQls_",
                    "position": 12,
                    "connectedRight": true,
                    "handles": [
                      0.5,
                      1,
                      0.5,
                      0
                    ],
                    "type": "bezier",
                    "value": 20.479472219256753
                  },
                  {
                    "id": "h-RA9VaKOs",
                    "position": 14,
                    "connectedRight": true,
                    "handles": [
                      0.5,
                      1,
                      0.5,
                      0
                    ],
                    "type": "bezier",
                    "value": 0.3543246692039643
                  },
                  {
                    "id": "kXkUddQEZE",
                    "position": 16,
                    "connectedRight": true,
                    "handles": [
                      0.5,
                      1,
                      0.5,
                      0
                    ],
                    "type": "bezier",
                    "value": 0.6253065665105542
                  },
                  {
                    "id": "Ak5IE0biK9",
                    "position": 20,
                    "connectedRight": true,
                    "handles": [
                      0.5,
                      1,
                      0.5,
                      0
                    ],
                    "type": "bezier",
                    "value": 20.479472219256753
                  },
                  {
                    "id": "xELQftOA41",
                    "position": 22,
                    "connectedRight": true,
                    "handles": [
                      0.5,
                      1,
                      0.5,
                      0
                    ],
                    "type": "bezier",
                    "value": 1.0891750560611406
                  },
                  {
                    "id": "xfWwG4TRKP",
                    "position": 24,
                    "connectedRight": true,
                    "handles": [
                      0.5,
                      1,
                      0.5,
                      0
                    ],
                    "type": "bezier",
                    "value": 1.039173474391232
                  },
                  {
                    "id": "Er0e4VEoZi",
                    "position": 28,
                    "connectedRight": true,
                    "handles": [
                      0.5,
                      1,
                      0.5,
                      0
                    ],
                    "type": "bezier",
                    "value": 20.479472219256753
                  },
                  {
                    "id": "H-GK4ZpkTf",
                    "position": 30,
                    "connectedRight": true,
                    "handles": [
                      0.5,
                      1,
                      0.5,
                      0
                    ],
                    "type": "bezier",
                    "value": 0.03707921730400088
                  },
                  {
                    "id": "GFOK4ehA_z",
                    "position": 32,
                    "connectedRight": true,
                    "handles": [
                      0.5,
                      1,
                      0.5,
                      0
                    ],
                    "type": "bezier",
                    "value": 0.9527926209198059
                  },
                  {
                    "id": "mVlpwIK0id",
                    "position": 36,
                    "connectedRight": true,
                    "handles": [
                      0.5,
                      1,
                      0.5,
                      0
                    ],
                    "type": "bezier",
                    "value": 20.479472219256753
                  }
                ]
              },
              "pVMXtVqx46": {
                "type": "BasicKeyframedTrack",
                "__debugName": "Camera:[\"position\",\"z\"]",
                "keyframes": [
                  {
                    "id": "Hb_udSOY5r",
                    "position": 0,
                    "connectedRight": true,
                    "handles": [
                      0.5,
                      1,
                      0.5,
                      0
                    ],
                    "type": "bezier",
                    "value": 207.72099875120463
                  },
                  {
                    "id": "zAGfvaI2tk",
                    "position": 4,
                    "connectedRight": true,
                    "handles": [
                      0.5,
                      1,
                      0.5,
                      0
                    ],
                    "type": "bezier",
                    "value": 34.79649601311954
                  },
                  {
                    "id": "ff1gUE6sNE",
                    "position": 6,
                    "connectedRight": true,
                    "handles": [
                      0.5,
                      1,
                      0.5,
                      0
                    ],
                    "type": "bezier",
                    "value": 34.79649601311954
                  },
                  {
                    "id": "4LKA0uG970",
                    "position": 8,
                    "connectedRight": true,
                    "handles": [
                      0.5,
                      1,
                      0.5,
                      0
                    ],
                    "type": "bezier",
                    "value": 2.2134499213523853
                  },
                  {
                    "id": "a3Uhytz6r9",
                    "position": 12,
                    "connectedRight": true,
                    "handles": [
                      0.5,
                      1,
                      0.5,
                      0
                    ],
                    "type": "bezier",
                    "value": 34.79649601311954
                  },
                  {
                    "id": "LGnctV5gzY",
                    "position": 14,
                    "connectedRight": true,
                    "handles": [
                      0.5,
                      1,
                      0.5,
                      0
                    ],
                    "type": "bezier",
                    "value": 34.79649601311954
                  },
                  {
                    "id": "pusXKrFnFj",
                    "position": 16,
                    "connectedRight": true,
                    "handles": [
                      0.5,
                      1,
                      0.5,
                      0
                    ],
                    "type": "bezier",
                    "value": 2.085583029795708
                  },
                  {
                    "id": "qcGlQwhyq2",
                    "position": 20,
                    "connectedRight": true,
                    "handles": [
                      0.5,
                      1,
                      0.5,
                      0
                    ],
                    "type": "bezier",
                    "value": 34.79649601311954
                  },
                  {
                    "id": "ET-5ZQET0k",
                    "position": 22,
                    "connectedRight": true,
                    "handles": [
                      0.5,
                      1,
                      0.5,
                      0
                    ],
                    "type": "bezier",
                    "value": 34.79649601311954
                  },
                  {
                    "id": "vscPqaurSX",
                    "position": 24,
                    "connectedRight": true,
                    "handles": [
                      0.5,
                      1,
                      0.5,
                      0
                    ],
                    "type": "bezier",
                    "value": 1.8043196071879937
                  },
                  {
                    "id": "q8kmQMdEgs",
                    "position": 28,
                    "connectedRight": true,
                    "handles": [
                      0.5,
                      1,
                      0.5,
                      0
                    ],
                    "type": "bezier",
                    "value": 34.79649601311954
                  },
                  {
                    "id": "103z7wuO6V",
                    "position": 30,
                    "connectedRight": true,
                    "handles": [
                      0.5,
                      1,
                      0.5,
                      0
                    ],
                    "type": "bezier",
                    "value": 34.79649601311954
                  },
                  {
                    "id": "Yiy83d39Xr",
                    "position": 32,
                    "connectedRight": true,
                    "handles": [
                      0.5,
                      1,
                      0.5,
                      0
                    ],
                    "type": "bezier",
                    "value": 2.20525639358712
                  },
                  {
                    "id": "l2V-zpv9sk",
                    "position": 36,
                    "connectedRight": true,
                    "handles": [
                      0.5,
                      1,
                      0.5,
                      0
                    ],
                    "type": "bezier",
                    "value": 34.79649601311954
                  }
                ]
              }
            },
            "trackIdByPropPath": {
              "[\"position\",\"x\"]": "pR6XONmeJe",
              "[\"position\",\"y\"]": "dDvO1bpiqm",
              "[\"position\",\"z\"]": "pVMXtVqx46"
            }
          },
          "Camera Target": {
            "trackData": {
              "IGcMT37jIG": {
                "type": "BasicKeyframedTrack",
                "__debugName": "Camera Target:[\"position\",\"x\"]",
                "keyframes": [
                  {
                    "id": "kS3ABw-4H3",
                    "position": 0,
                    "connectedRight": true,
                    "handles": [
                      0.5,
                      1,
                      0.5,
                      0
                    ],
                    "type": "bezier",
                    "value": 0
                  },
                  {
                    "id": "C65-dRonyW",
                    "position": 4,
                    "connectedRight": true,
                    "handles": [
                      0.5,
                      1,
                      0.5,
                      0
                    ],
                    "type": "bezier",
                    "value": -0.056917015409226224
                  },
                  {
                    "id": "95xWrfb6WH",
                    "position": 6,
                    "connectedRight": true,
                    "handles": [
                      0.5,
                      1,
                      0.5,
                      0
                    ],
                    "type": "bezier",
                    "value": -14.9258839100577
                  },
                  {
                    "id": "VP19Y0Fdxf",
                    "position": 8,
                    "connectedRight": true,
                    "handles": [
                      0.5,
                      1,
                      0.5,
                      0
                    ],
                    "type": "bezier",
                    "value": -15.066499348975544
                  },
                  {
                    "id": "kLyyML-S-a",
                    "position": 12,
                    "connectedRight": true,
                    "handles": [
                      0.5,
                      1,
                      0.5,
                      0
                    ],
                    "type": "bezier",
                    "value": -0.056917015409226224
                  },
                  {
                    "id": "b0Ic-WD8Ch",
                    "position": 14,
                    "connectedRight": true,
                    "handles": [
                      0.5,
                      1,
                      0.5,
                      0
                    ],
                    "type": "bezier",
                    "value": -5.030415133679766
                  },
                  {
                    "id": "_nNAMsCwiB",
                    "position": 16,
                    "connectedRight": true,
                    "handles": [
                      0.5,
                      1,
                      0.5,
                      0
                    ],
                    "type": "bezier",
                    "value": -4.925580210545585
                  },
                  {
                    "id": "m3EU4_TXGW",
                    "position": 20,
                    "connectedRight": true,
                    "handles": [
                      0.5,
                      1,
                      0.5,
                      0
                    ],
                    "type": "bezier",
                    "value": -0.056917015409226224
                  },
                  {
                    "id": "qweNa9Fe40",
                    "position": 22,
                    "connectedRight": true,
                    "handles": [
                      0.5,
                      1,
                      0.5,
                      0
                    ],
                    "type": "bezier",
                    "value": 5.839508714062926
                  },
                  {
                    "id": "30VecDxEyO",
                    "position": 24,
                    "connectedRight": true,
                    "handles": [
                      0.5,
                      1,
                      0.5,
                      0
                    ],
                    "type": "bezier",
                    "value": 5.785373851235063
                  },
                  {
                    "id": "z6D36gnykm",
                    "position": 28,
                    "connectedRight": true,
                    "handles": [
                      0.5,
                      1,
                      0.5,
                      0
                    ],
                    "type": "bezier",
                    "value": -0.056917015409226224
                  },
                  {
                    "id": "Ecu8yicdT1",
                    "position": 30,
                    "connectedRight": true,
                    "handles": [
                      0.5,
                      1,
                      0.5,
                      0
                    ],
                    "type": "bezier",
                    "value": 15.265828950844499
                  },
                  {
                    "id": "ODQXchsfot",
                    "position": 32,
                    "connectedRight": true,
                    "handles": [
                      0.5,
                      1,
                      0.5,
                      0
                    ],
                    "type": "bezier",
                    "value": 15.265828950844499
                  },
                  {
                    "id": "RPzsXCdlNx",
                    "position": 36,
                    "connectedRight": true,
                    "handles": [
                      0.5,
                      1,
                      0.5,
                      0
                    ],
                    "type": "bezier",
                    "value": -0.056917015409226224
                  }
                ]
              },
              "cU8S7g4E7s": {
                "type": "BasicKeyframedTrack",
                "__debugName": "Camera Target:[\"position\",\"y\"]",
                "keyframes": [
                  {
                    "id": "YJ-GzNO0FJ",
                    "position": 0,
                    "connectedRight": true,
                    "handles": [
                      0.5,
                      1,
                      0.5,
                      0
                    ],
                    "type": "bezier",
                    "value": 0
                  },
                  {
                    "id": "0doZpXaQAB",
                    "position": 4,
                    "connectedRight": true,
                    "handles": [
                      0.5,
                      1,
                      0.5,
                      0
                    ],
                    "type": "bezier",
                    "value": 0
                  },
                  {
                    "id": "PMSF0C_HFo",
                    "position": 6,
                    "connectedRight": true,
                    "handles": [
                      0.5,
                      1,
                      0.5,
                      0
                    ],
                    "type": "bezier",
                    "value": 0
                  },
                  {
                    "id": "uFF2jzmeFT",
                    "position": 8,
                    "connectedRight": true,
                    "handles": [
                      0.5,
                      1,
                      0.5,
                      0
                    ],
                    "type": "bezier",
                    "value": -0.23411013454677532
                  },
                  {
                    "id": "B6lJC3wbsd",
                    "position": 12,
                    "connectedRight": true,
                    "handles": [
                      0.5,
                      1,
                      0.5,
                      0
                    ],
                    "type": "bezier",
                    "value": 0
                  },
                  {
                    "id": "Zba4PZwt5Z",
                    "position": 14,
                    "connectedRight": true,
                    "handles": [
                      0.5,
                      1,
                      0.5,
                      0
                    ],
                    "type": "bezier",
                    "value": 0
                  },
                  {
                    "id": "mbJUuLuq-f",
                    "position": 16,
                    "connectedRight": true,
                    "handles": [
                      0.5,
                      1,
                      0.5,
                      0
                    ],
                    "type": "bezier",
                    "value": -0.0993240003614404
                  },
                  {
                    "id": "WHuHVnzYSf",
                    "position": 20,
                    "connectedRight": true,
                    "handles": [
                      0.5,
                      1,
                      0.5,
                      0
                    ],
                    "type": "bezier",
                    "value": 0
                  },
                  {
                    "id": "agTgLjrv1g",
                    "position": 22,
                    "connectedRight": true,
                    "handles": [
                      0.5,
                      1,
                      0.5,
                      0
                    ],
                    "type": "bezier",
                    "value": 0
                  },
                  {
                    "id": "hnpXE_8fP1",
                    "position": 24,
                    "connectedRight": true,
                    "handles": [
                      0.5,
                      1,
                      0.5,
                      0
                    ],
                    "type": "bezier",
                    "value": -0.20181239657296146
                  },
                  {
                    "id": "RuozyWvXLI",
                    "position": 28,
                    "connectedRight": true,
                    "handles": [
                      0.5,
                      1,
                      0.5,
                      0
                    ],
                    "type": "bezier",
                    "value": 0
                  },
                  {
                    "id": "OclV1vdfgb",
                    "position": 30,
                    "connectedRight": true,
                    "handles": [
                      0.5,
                      1,
                      0.5,
                      0
                    ],
                    "type": "bezier",
                    "value": 0
                  },
                  {
                    "id": "f-yjojx2W3",
                    "position": 32,
                    "connectedRight": true,
                    "handles": [
                      0.5,
                      1,
                      0.5,
                      0
                    ],
                    "type": "bezier",
                    "value": 0
                  },
                  {
                    "id": "RgR6zqNo5k",
                    "position": 36,
                    "connectedRight": true,
                    "handles": [
                      0.5,
                      1,
                      0.5,
                      0
                    ],
                    "type": "bezier",
                    "value": 0
                  }
                ]
              },
              "aDoueRvWAM": {
                "type": "BasicKeyframedTrack",
                "__debugName": "Camera Target:[\"position\",\"z\"]",
                "keyframes": [
                  {
                    "id": "s9hPFZzB0x",
                    "position": 0,
                    "connectedRight": true,
                    "handles": [
                      0.5,
                      1,
                      0.5,
                      0
                    ],
                    "type": "bezier",
                    "value": 0
                  },
                  {
                    "id": "v8iCQQfyOI",
                    "position": 4,
                    "connectedRight": true,
                    "handles": [
                      0.5,
                      1,
                      0.5,
                      0
                    ],
                    "type": "bezier",
                    "value": 0
                  },
                  {
                    "id": "AFDxNkUG39",
                    "position": 6,
                    "connectedRight": true,
                    "handles": [
                      0.5,
                      1,
                      0.5,
                      0
                    ],
                    "type": "bezier",
                    "value": 0
                  },
                  {
                    "id": "bUBpY-X9ix",
                    "position": 8,
                    "connectedRight": true,
                    "handles": [
                      0.5,
                      1,
                      0.5,
                      0
                    ],
                    "type": "bezier",
                    "value": -0.20261133168770584
                  },
                  {
                    "id": "0Pt8WJZ_Cj",
                    "position": 12,
                    "connectedRight": true,
                    "handles": [
                      0.5,
                      1,
                      0.5,
                      0
                    ],
                    "type": "bezier",
                    "value": 0
                  },
                  {
                    "id": "kffan9uu6_",
                    "position": 14,
                    "connectedRight": true,
                    "handles": [
                      0.5,
                      1,
                      0.5,
                      0
                    ],
                    "type": "bezier",
                    "value": 0
                  },
                  {
                    "id": "yBaGQUckpy",
                    "position": 16,
                    "connectedRight": true,
                    "handles": [
                      0.5,
                      1,
                      0.5,
                      0
                    ],
                    "type": "bezier",
                    "value": 0.34800104130983645
                  },
                  {
                    "id": "mWp7wB6iLB",
                    "position": 20,
                    "connectedRight": true,
                    "handles": [
                      0.5,
                      1,
                      0.5,
                      0
                    ],
                    "type": "bezier",
                    "value": 0
                  },
                  {
                    "id": "vvrmz060gW",
                    "position": 22,
                    "connectedRight": true,
                    "handles": [
                      0.5,
                      1,
                      0.5,
                      0
                    ],
                    "type": "bezier",
                    "value": 0
                  },
                  {
                    "id": "IfAt0BBJ1U",
                    "position": 24,
                    "connectedRight": true,
                    "handles": [
                      0.5,
                      1,
                      0.5,
                      0
                    ],
                    "type": "bezier",
                    "value": 0.4305670025042887
                  },
                  {
                    "id": "mDhXapgFuS",
                    "position": 28,
                    "connectedRight": true,
                    "handles": [
                      0.5,
                      1,
                      0.5,
                      0
                    ],
                    "type": "bezier",
                    "value": 0
                  },
                  {
                    "id": "xCHyssA3hQ",
                    "position": 30,
                    "connectedRight": true,
                    "handles": [
                      0.5,
                      1,
                      0.5,
                      0
                    ],
                    "type": "bezier",
                    "value": 0
                  },
                  {
                    "id": "mtLUrWTSer",
                    "position": 32,
                    "connectedRight": true,
                    "handles": [
                      0.5,
                      1,
                      0.5,
                      0
                    ],
                    "type": "bezier",
                    "value": 0
                  },
                  {
                    "id": "VR9JzoNaaE",
                    "position": 36,
                    "connectedRight": true,
                    "handles": [
                      0.5,
                      1,
                      0.5,
                      0
                    ],
                    "type": "bezier",
                    "value": 0
                  }
                ]
              }
            },
            "trackIdByPropPath": {
              "[\"position\",\"x\"]": "IGcMT37jIG",
              "[\"position\",\"y\"]": "cU8S7g4E7s",
              "[\"position\",\"z\"]": "aDoueRvWAM"
            }
          }
        }
      }
    }
  },
  "definitionVersion": "0.4.0",
  "revisionHistory": [
    "bGfgMoz5JeVSZAdR"
  ]
}